procli/__init__.py
procli-0.0.0.dist-info/METADATA
procli-0.0.0.dist-info/WHEEL
procli-0.0.0.dist-info/top_level.txt
procli-0.0.0.dist-info/RECORD
